cascadetoml.py
cascadetoml-0.3.3.dist-info/entry_points.txt
cascadetoml-0.3.3.dist-info/LICENSE
cascadetoml-0.3.3.dist-info/WHEEL
cascadetoml-0.3.3.dist-info/METADATA
cascadetoml-0.3.3.dist-info/RECORD
