Metadata-Version: 2.1
Name: cascadetoml
Version: 0.3.3
Summary: Command for cascading toml files together
Home-page: https://github.com/adafruit/cascadetoml
Author: Scott Shawcroft
Author-email: scott@tannewt.org
Classifier: License :: OSI Approved :: MIT License
Requires-Dist: parse
Requires-Dist: tabulate
Requires-Dist: tomlkit>=0.8.0
Requires-Dist: typer
